bionemo/llm/__init__.py
bionemo/llm/api.py
bionemo/llm/lightning.py
bionemo/llm/train.py
bionemo/llm/data/__init__.py
bionemo/llm/data/collate.py
bionemo/llm/data/datamodule.py
bionemo/llm/data/label2id_tokenizer.py
bionemo/llm/data/masking.py
bionemo/llm/data/types.py
bionemo/llm/model/__init__.py
bionemo/llm/model/config.py
bionemo/llm/model/layers.py
bionemo/llm/model/loss.py
bionemo/llm/model/lr_scheduler.py
bionemo/llm/model/biobert/__init__.py
bionemo/llm/model/biobert/lightning.py
bionemo/llm/model/biobert/model.py
bionemo/llm/model/biobert/testing_utils.py
bionemo/llm/model/biobert/transformer_specs.py
bionemo/llm/run/__init__.py
bionemo/llm/run/config_models.py
bionemo/llm/utils/__init__.py
bionemo/llm/utils/callbacks.py
bionemo/llm/utils/datamodule_utils.py
bionemo/llm/utils/iomixin_utils.py
bionemo/llm/utils/logger_utils.py
bionemo/llm/utils/megatron_utils.py
bionemo/llm/utils/remote.py
bionemo/llm/utils/weight_utils.py
bionemo_llm-2.4.5.dist-info/licenses/LICENSE
bionemo_llm-2.4.5.dist-info/METADATA
bionemo_llm-2.4.5.dist-info/WHEEL
bionemo_llm-2.4.5.dist-info/top_level.txt
bionemo_llm-2.4.5.dist-info/RECORD
