Metadata-Version: 2.4
Name: bionemo-llm
Version: 2.4.5
Summary: BioNeMo Large Language Model Components using NeMo and Megatron
Author-email: BioNeMo Team <bionemofeedback@nvidia.com>
Requires-Python: >=3.10
License-File: LICENSE
Requires-Dist: bionemo-core
Requires-Dist: lightning>=2.2.1
Requires-Dist: megatron-core
Requires-Dist: nemo_toolkit[nlp]>=2.2.1
Requires-Dist: nemo-run
Requires-Dist: hatchling
Provides-Extra: test
Requires-Dist: bionemo-testing; extra == "test"
Provides-Extra: te
Requires-Dist: transformer_engine[pytorch]; extra == "te"
Dynamic: license-file
